docviz/__init__.py
docviz/constants.py
docviz/logging.py
docviz/lib/__init__.py
docviz/lib/functions.py
docviz/lib/detection/__init__.py
docviz/lib/detection/deduplication.py
docviz/lib/detection/frontend.py
docviz/lib/detection/labels.py
docviz/lib/detection/backends/__init__.py
docviz/lib/detection/backends/base.py
docviz/lib/detection/backends/doclayout_yolo.py
docviz/lib/detection/backends/yolo_doclaynet.py
docviz/lib/document/__init__.py
docviz/lib/document/convert.py
docviz/lib/document/document.py
docviz/lib/document/pdf_analyzer.py
docviz/lib/document/text_extraction.py
docviz/lib/extraction/pipeline.py
docviz/lib/extraction/utils.py
docviz/lib/image/__init__.py
docviz/lib/image/annotate.py
docviz/lib/image/preprocessing.py
docviz/lib/image/summarizer.py
docviz/types/__init__.py
docviz/types/aliases.py
docviz/types/detection_config.py
docviz/types/detection_result.py
docviz/types/extraction_config.py
docviz/types/extraction_result.py
docviz/types/extraction_type.py
docviz/types/save_format.py
docviz_python-1.0.1.dist-info/licenses/LICENSE
docviz_python-1.0.1.dist-info/METADATA
docviz_python-1.0.1.dist-info/WHEEL
docviz_python-1.0.1.dist-info/top_level.txt
docviz_python-1.0.1.dist-info/RECORD
