Metadata-Version: 2.4
Name: docviz-python
Version: 1.0.1
Summary: A Python library for extracting and analyzing content from any documents, supporting batch and selective extraction, custom configuration, and multiple output formats.
Author: fresh-milkshake
License: MIT License
Keywords: pdf,document analysis,extraction,scientific papers,batch processing
Classifier: Programming Language :: Python :: 3
Classifier: License :: OSI Approved :: MIT License
Classifier: Operating System :: OS Independent
Classifier: Intended Audience :: Science/Research
Classifier: Topic :: Text Processing :: Linguistic
Classifier: Topic :: Scientific/Engineering :: Information Analysis
Requires-Python: >=3.10
License-File: LICENSE
Requires-Dist: click>=8.2.1
Requires-Dist: loguru>=0.7.3
Requires-Dist: openai>=1.98.0
Requires-Dist: opencv-python>=4.12.0.88
Requires-Dist: pymupdf>=1.26.3
Requires-Dist: pytesseract>=0.3.13
Provides-Extra: dev
Requires-Dist: doclayout-yolo>=0.0.4; extra == "dev"
Requires-Dist: huggingface-hub>=0.34.3; extra == "dev"
Requires-Dist: jupyter>=1.1.1; extra == "dev"
Requires-Dist: pyright>=1.1.403; extra == "dev"
Requires-Dist: ruff>=0.12.7; extra == "dev"
Provides-Extra: showcase
Requires-Dist: ipykernel>=6.30.1; extra == "showcase"
Requires-Dist: seaborn>=0.13.2; extra == "showcase"
Requires-Dist: ultralytics>=8.3.174; extra == "showcase"
Dynamic: license-file
